{
  "end_date": "2024-11-09T03:07:45.550499",
  "start_date": "2024-10-12T03:04:22.044647",
  "repos": [
    {
      "name": "identicons",
      "commits_count": 0,
      "additions": 0,
      "deletions": 0
    },
    {
      "name": "nimiq-utils",
      "commits_count": 14,
      "additions": 235,
      "deletions": -144
    },
    {
      "name": "ledger-api",
      "commits_count": 9,
      "additions": 147,
      "deletions": -92
    },
    {
      "name": "mining-pool",
      "commits_count": 0,
      "additions": 0,
      "deletions": 0
    },
    {
      "name": "ledger-app-nimiq",
      "commits_count": 0,
      "additions": 0,
      "deletions": 0
    },
    {
      "name": "keyguard",
      "commits_count": 11,
      "additions": 997,
      "deletions": -200
    },
    {
      "name": "hub",
      "commits_count": 11,
      "additions": 1391,
      "deletions": -1131
    },
    {
      "name": "core-rs-albatross",
      "commits_count": 43,
      "additions": 2146,
      "deletions": -1632
    },
    {
      "name": "wallet",
      "commits_count": 64,
      "additions": 14265,
      "deletions": -7613
    },
    {
      "name": "fastspot-api",
      "commits_count": 15,
      "additions": 404,
      "deletions": -144
    },
    {
      "name": "oasis-api-js",
      "commits_count": 4,
      "additions": 239,
      "deletions": -67
    },
    {
      "name": "libswap-js",
      "commits_count": 11,
      "additions": 464,
      "deletions": -294
    },
    {
      "name": "crypto-map",
      "commits_count": 12,
      "additions": 159,
      "deletions": -82
    },
    {
      "name": "developer-center",
      "commits_count": 12,
      "additions": 1716,
      "deletions": -1713
    },
    {
      "name": "validators-api",
      "commits_count": 90,
      "additions": 13701,
      "deletions": -10658
    },
    {
      "name": "prestaking-website",
      "commits_count": 17,
      "additions": 411,
      "deletions": -574
    },
    {
      "name": "nimiq-website",
      "commits_count": 23,
      "additions": 20146,
      "deletions": -10052
    }
  ]
}